.class public MiniB
.super java/lang/Object

.method public static len(Ljava/lang/String;)I
    .limit stack 1
    .limit locals 1

    aload_0

    ; El String ya está en la cima de la pila
    invokevirtual java/lang/String/length()I

    ; Retorna el resultado (que ya está en la pila)
    ireturn
.end method

.method public static isNan(Ljava/lang/Object;)I
    .limit stack 2
    .limit locals 1

    ; Comprobar si el valor es null
    aload_0            ; Cargar el parámetro en la pila
    ifnull ReturnTrue  ; Si es null, ir a ReturnTrue

    ; Comprobar si el valor es una instancia de Double o Float (para NaN)
    aload_0
    instanceof java/lang/Double
    ifeq CheckFloat    ; Si no es Double, verificar Float

    ; Comprobar si es NaN en Double
    aload_0
    checkcast java/lang/Double
    invokevirtual java/lang/Double/isNaN()Z
    ifne ReturnTrue    ; Si es NaN, ir a ReturnTrue
    goto ReturnFalse

CheckFloat:
    aload_0
    instanceof java/lang/Float
    ifeq ReturnFalse   ; Si no es Float, no es NaN

    ; Comprobar si es NaN en Float
    aload_0
    checkcast java/lang/Float
    invokevirtual java/lang/Float/isNaN()Z
    ifne ReturnTrue    ; Si es NaN, ir a ReturnTrue

ReturnFalse:
    iconst_0           ; Devuelve 0 si no es null ni NaN
    ireturn

ReturnTrue:
    iconst_1           ; Devuelve 1 si es null o NaN
    ireturn

.end method

.method public static main([Ljava/lang/String;)V
    .limit stack 100
    .limit locals 100
    getstatic java/lang/System/out Ljava/io/PrintStream;
    ldc 123
    invokevirtual java/io/PrintStream/println(I)V
    getstatic java/lang/System/out Ljava/io/PrintStream;
    ldc "12345"
    invokestatic MiniB/len(Ljava/lang/String;)I
    invokevirtual java/io/PrintStream/println(I)V
    getstatic java/lang/System/out Ljava/io/PrintStream;
    aconst_null
    invokevirtual java/io/PrintStream/println(Ljava/lang/Object;)V
    return
.end method
